setup.py
firval/__init__.py
firval.egg-info/PKG-INFO
firval.egg-info/SOURCES.txt
firval.egg-info/dependency_links.txt
firval.egg-info/entry_points.txt
firval.egg-info/requires.txt
firval.egg-info/top_level.txt