Metadata-Version: 1.1
Name: firval
Version: 1.2
Summary: a netfilter firewall rules generator designed designed to be easy to read, write and maintain
Home-page: https://github.com/nlm/firval
Author: Nicolas Limage
Author-email: UNKNOWN
License: MIT
Keywords: netfilter iptables firewall
Platform: UNKNOWN
Classifier: Development Status :: 5 - Production/Stable
Classifier: Environment :: Console
Classifier: Intended Audience :: System Administrators
Classifier: License :: OSI Approved :: MIT License
Classifier: Operating System :: POSIX :: Linux
Classifier: Programming Language :: Python
Classifier: Topic :: System :: Networking :: Firewalls
